{
  "project_info": {
    "project_number": "877981756963",
    "firebase_url": "https://filipinofooddelicacies-c2fc7.firebaseio.com",
    "project_id": "filipinofooddelicacies-c2fc7",
    "storage_bucket": "filipinofooddelicacies-c2fc7.appspot.com"
  },
  "client": [
    {
      "client_info": {
        "mobilesdk_app_id": "1:877981756963:android:d8a8a8e677c258e3",
        "android_client_info": {
          "package_name": "org.nativescript.FilipinoFoodDelicaciesApp"
        }
      },
      "oauth_client": [
        {
          "client_id": "877981756963-pqiai400su6a3k3u396ofet7p0a15k15.apps.googleusercontent.com",
          "client_type": 3
        }
      ],
      "api_key": [
        {
          "current_key": "AIzaSyALznaE-DKZRPLad6hxPzFzs0Q1eMebGGI"
        }
      ],
      "services": {
        "analytics_service": {
          "status": 1
        },
        "appinvite_service": {
          "status": 1,
          "other_platform_oauth_client": []
        },
        "ads_service": {
          "status": 2
        }
      }
    }
  ],
  "configuration_version": "1"
}